rozetka/__init__.py
rozetka/entities/__init__.py
rozetka/entities/category.py
rozetka/entities/item.py
rozetka/entities/point.py
rozetka/entities/supercategory.py
rozetka/examples/example_category.py
rozetka/examples/example_item.py
rozetka/runners/parse_api.py
rozetka/tools/__init__.py
rozetka/tools/constants.py
rozetka/tools/db.py
rozetka/tools/tools.py
rozetka_api-1.7.0.dist-info/METADATA
rozetka_api-1.7.0.dist-info/WHEEL
rozetka_api-1.7.0.dist-info/licenses/AUTHORS.rst
rozetka_api-1.7.0.dist-info/RECORD
